dhmsaiffconverter/__init__.py
dhmsaiffconverter/aiff_data_download_tool.py
dhmsaiffconverter/convert_aiff.py
dhmsaiffconverter-1.0.dist-info/LICENSE.txt
dhmsaiffconverter-1.0.dist-info/METADATA
dhmsaiffconverter-1.0.dist-info/WHEEL
dhmsaiffconverter-1.0.dist-info/top_level.txt
dhmsaiffconverter-1.0.dist-info/RECORD
