Metadata-Version: 2.1
Name: dhmsaiffconverter
Version: 1.0
Summary: converter raw aiff vibration data to csv data file
Home-page: https://github.com/DJ0617/DHMS_aiff_to_csv
Author: David Bao
Author-email: daijiebao0617@outlook.com
Classifier: Programming Language :: Python :: 3
Classifier: License :: OSI Approved :: MIT License
Classifier: Operating System :: OS Independent
Requires-Python: >=3.6
License-File: LICENSE.txt
